guiguts/__main__.py
guiguts/application.py
guiguts/ascii_tables.py
guiguts/CHANGELOG.md
guiguts/checkers.py
guiguts/content_providing.py
guiguts/data/cp_files/fcannos.json
guiguts/data/cp_files/no_hyphen.json
guiguts/data/cp_files/scannos.json
guiguts/data/dictionaries/copyright_dict_de.txt
guiguts/data/dictionaries/copyright_dict_en.txt
guiguts/data/dictionaries/copyright_dict_es.txt
guiguts/data/dictionaries/copyright_dict_fr.txt
guiguts/data/dictionaries/copyright_dict_nl.txt
guiguts/data/dictionaries/copyright_dict_pt.txt
guiguts/data/dictionaries/dict_de_default.txt
guiguts/data/dictionaries/dict_en_default.txt
guiguts/data/dictionaries/dict_es_default.txt
guiguts/data/dictionaries/dict_fr_default.txt
guiguts/data/dictionaries/dict_nl_default.txt
guiguts/data/dictionaries/dict_pt_default.txt
guiguts/data/dictionaries/hebelist.txt
guiguts/data/html/html_header.txt
guiguts/data/icons/back.png
guiguts/data/icons/copy.png
guiguts/data/icons/cut.png
guiguts/data/icons/forward.png
guiguts/data/icons/help.png
guiguts/data/icons/license.txt
guiguts/data/icons/open.png
guiguts/data/icons/paste.png
guiguts/data/icons/redo.png
guiguts/data/icons/save.png
guiguts/data/icons/search.png
guiguts/data/icons/undo.png
guiguts/data/regex_library/dashes.json
guiguts/data/regex_library/italic_semantic.json
guiguts/data/scannos/en-common.json
guiguts/data/scannos/misspelled.json
guiguts/data/scannos/regex.json
guiguts/data/themes/awthemes-10.4.0/awdark.tcl
guiguts/data/themes/awthemes-10.4.0/awlight.tcl
guiguts/data/themes/awthemes-10.4.0/awtemplate.tcl
guiguts/data/themes/awthemes-10.4.0/awthemes.tcl
guiguts/data/themes/awthemes-10.4.0/colorutils.tcl
guiguts/data/themes/awthemes-10.4.0/i/awthemes/arrow/solid-bg/arrow-down-d.svg
guiguts/data/themes/awthemes-10.4.0/i/awthemes/arrow/solid-bg/arrow-down-n-base.svg
guiguts/data/themes/awthemes-10.4.0/i/awthemes/arrow/solid-bg/arrow-down-n.svg
guiguts/data/themes/awthemes-10.4.0/i/awthemes/arrow/solid-bg/arrow-left-d.svg
guiguts-2.0.15.dist-info/entry_points.txt
guiguts-2.0.15.dist-info/LICENSE.txt
guiguts-2.0.15.dist-info/METADATA
guiguts-2.0.15.dist-info/WHEEL
guiguts-2.0.15.dist-info/RECORD
