Metadata-Version: 2.3
Name: guiguts
Version: 2.0.15
Summary: Guiguts version 2, Python/tkinter version
Author: DP Guiguts Dev Team
Author-email: windymilla@users.noreply.github.com
Requires-Python: >=3.11,<4.0
Classifier: Programming Language :: Python :: 3
Classifier: Programming Language :: Python :: 3.11
Classifier: Programming Language :: Python :: 3.12
Classifier: Programming Language :: Python :: 3.13
Requires-Dist: Pillow (>=12.0,<13.0)
Requires-Dist: cssselect (>=1.3.0,<2.0.0)
Requires-Dist: darkdetect (>=0.8.0,<0.9.0)
Requires-Dist: html5lib (>=1.1,<2.0)
Requires-Dist: levenshtein (>=0.27.1,<0.28.0)
Requires-Dist: lxml (>=6.0.2,<7.0.0)
Requires-Dist: packaging (>=25.0,<26.0)
Requires-Dist: pywin32 (>=311,<312) ; sys_platform == "win32"
Requires-Dist: rapidfuzz (>=3.14.2,<4.0.0)
Requires-Dist: regex (>=2025.10.23,<2026.0.0)
Requires-Dist: requests (>=2.32.3,<3.0.0)
Requires-Dist: roman (>=5.1,<6.0)
Requires-Dist: tinycss (>=0.4,<0.5)
